pytest_inmanta/__init__.py
pytest_inmanta/plugin.py
pytest_inmanta-0.4.dist-info/DESCRIPTION.rst
pytest_inmanta-0.4.dist-info/METADATA
pytest_inmanta-0.4.dist-info/RECORD
pytest_inmanta-0.4.dist-info/WHEEL
pytest_inmanta-0.4.dist-info/entry_points.txt
pytest_inmanta-0.4.dist-info/metadata.json
pytest_inmanta-0.4.dist-info/pbr.json
pytest_inmanta-0.4.dist-info/top_level.txt
