Metadata-Version: 2.0
Name: pytest-inmanta
Version: 0.4
Summary: A py.test plugin providing fixtures to simplify inmanta modules testing.
Home-page: https://github.com/inmanta/pytest-inmanta
Author: Inmanta NV
Author-email: code@inmanta.com
License: Apache License, Version 2.0
Keywords: pytest py.test inmanta testing unit tests plugin
Platform: UNKNOWN
Classifier: Development Status :: 5 - Production/Stable
Classifier: Environment :: Plugins
Classifier: Intended Audience :: Developers
Classifier: License :: OSI Approved :: Apache Software License
Classifier: Operating System :: OS Independent
Classifier: Programming Language :: Python
Classifier: Programming Language :: Python :: 3
Classifier: Topic :: Software Development
Classifier: Topic :: Software Development :: Testing
Requires-Dist: pytest
Requires-Dist: inmanta
